techzapi/api.py
techzapi-1.2.1.dist-info/LICENSE
techzapi-1.2.1.dist-info/METADATA
techzapi-1.2.1.dist-info/WHEEL
techzapi-1.2.1.dist-info/top_level.txt
techzapi-1.2.1.dist-info/RECORD
