Metadata-Version: 2.1
Name: techzapi
Version: 1.2.1
Summary: Python wrapper for the TechZApi
Home-page: https://github.com/TechShreyash/TechZApi
Author: TechShreyash
Author-email: techshreyash123@gmail.com
License: MIT
Keywords: API,TechZApi,TechZAPI,TechZBots,GogoAnime,Anime,AnimeAPI,MkvCinemas,MkvCinemasAPI,Scrapper
License-File: LICENSE
Requires-Dist: requests
